wzone/__init__.py
wzone/wzone.py
wzone/data/ged_summary.pkl
wzone/data/w_date/ged_optimal_parameters.pkl
wzone/data/w_date/ged_osvm_dict.gzip
wzone/data/w_date/ged_osvm_dict_light.pkl
wzone/data/w_date/ged_scaler.pkl
wzone/data/wo_date/ged_optimal_parameters.pkl
wzone/data/wo_date/ged_osvm_dict.gzip
wzone/data/wo_date/ged_osvm_dict_light.pkl
wzone/data/wo_date/ged_scaler.pkl
wzone-0.2.4.dist-info/DESCRIPTION.rst
wzone-0.2.4.dist-info/METADATA
wzone-0.2.4.dist-info/RECORD
wzone-0.2.4.dist-info/WHEEL
wzone-0.2.4.dist-info/metadata.json
wzone-0.2.4.dist-info/top_level.txt
