Metadata-Version: 2.0
Name: wzone
Version: 0.2.4
Summary: Package for making zones of armed conflicts.
Home-page: http://github.com/kyosuke-kkt/wzone
Author: Kyosuke Kikuta
Author-email: kyosuke.kkt@outlook.com
License: GPL-3
Platform: UNKNOWN
Classifier: Development Status :: 3 - Alpha
Classifier: Environment :: Console
Classifier: Intended Audience :: End Users/Desktop
Classifier: License :: OSI Approved :: MIT License
Classifier: Operating System :: Microsoft :: Windows :: Windows 10
Classifier: Operating System :: MacOS :: MacOS X
Classifier: Programming Language :: Python :: 2.7
Classifier: Topic :: Software Development :: Libraries :: Python Modules
Requires-Python: >=2.7, <3.0
Requires-Dist: numpy (>=1.11.3)
Requires-Dist: pandas (>=0.18.1)
Requires-Dist: sklearn (>=0.0)
